hxm_refuel/__init__.py
hxm_refuel/bloomberg/__init__.py
hxm_refuel/bloomberg/bloomberg_api.py
hxm_refuel/bloomberg/bloomberg_recipies.py
hxm_refuel/bloomberg/bloomberg_sample.py
hxm_refuel/jeeves.py
hxm_refuel/snowflake/snowflake_recipes.py
hxm_refuel/snowflake/sql_recipes.py
hxm_refuel/snowpark/__init__.py
hxm_refuel/snowpark/recipies.py
hxm_refuel/snowpark/rsa.py
hxm_refuel/snowpark/sessions.py
hxm_refuel/validation.py
hxm_refuel-0.3.5.dist-info/LICENSE
hxm_refuel-0.3.5.dist-info/METADATA
hxm_refuel-0.3.5.dist-info/WHEEL
hxm_refuel-0.3.5.dist-info/RECORD
