Metadata-Version: 2.1
Name: hxm-refuel
Version: 0.3.5
Summary: Wrapper for financial database APIs & Snowpark
Author: djmcnay
Author-email: 39102979+djmcnay@users.noreply.github.com
Requires-Python: >=3.10,<3.13
Classifier: Programming Language :: Python :: 3
Classifier: Programming Language :: Python :: 3.10
Classifier: Programming Language :: Python :: 3.11
Classifier: Programming Language :: Python :: 3.12
Requires-Dist: toml (>=0.10.2,<0.11.0)
Requires-Dist: xbbg (>=0.7.7,<0.8.0)
